libspot.abi3.so
libspot-2.0b6.dist-info/METADATA
libspot-2.0b6.dist-info/WHEEL
libspot-2.0b6.dist-info/top_level.txt
libspot-2.0b6.dist-info/RECORD
